{
	"ImportPath": "github.com/sso-app",
	"GoVersion": "go1.9",
	"GodepVersion": "v79",
	"Deps": [
		{
			"ImportPath": "github.com/auth0/go-jwt-middleware",
			"Rev": "5493cabe49f7bfa6e2ec444a09d334d90cd4e2bd"
		},
		{
			"ImportPath": "github.com/codegangsta/negroni",
			"Comment": "v0.3.0-2-gcc68f18",
			"Rev": "cc68f18cd7e1157c71811df1396496a9db0e997d"
		},
		{
			"ImportPath": "github.com/davecgh/go-spew/spew",
			"Comment": "v1.1.0-9-gecdeabc",
			"Rev": "ecdeabc65495df2dec95d7c4a4c3e021903035e5"
		},
		{
			"ImportPath": "github.com/dgrijalva/jwt-go",
			"Comment": "v3.1.0",
			"Rev": "dbeaa9332f19a944acb5736b4456cfcc02140e29"
		},
		{
			"ImportPath": "github.com/gorilla/mux",
			"Comment": "v1.6.0-6-g5ab525f",
			"Rev": "5ab525f4fb1678e197ae59401e9050fa0b6cb5fd"
		},
		{
			"ImportPath": "github.com/pmezard/go-difflib/difflib",
			"Comment": "v1.0.0",
			"Rev": "792786c7400a136282c1664665ae0a8db921c6c2"
		},
		{
			"ImportPath": "github.com/stretchr/testify/assert",
			"Comment": "v1.1.4-72-g2aa2c17",
			"Rev": "2aa2c176b9dab406a6970f6a55f513e8a8c8b18f"
		}
	]
}
